flatland/__init__.py
flatland/runner.py
cg_flatland-0.0.1.dist-info/LICENSE
cg_flatland-0.0.1.dist-info/METADATA
cg_flatland-0.0.1.dist-info/WHEEL
cg_flatland-0.0.1.dist-info/top_level.txt
cg_flatland-0.0.1.dist-info/RECORD
