Metadata-Version: 2.1
Name: cg-flatland
Version: 0.0.1
Summary: Easier development of polymer structure prediction tools.
Home-page: https://github.com/cayleygroup/flatland
Author: The Cayley Group
Author-email: contact@cayleygroup.org
License: UNKNOWN
Platform: UNKNOWN
Classifier: Programming Language :: Python :: 3
Classifier: License :: OSI Approved :: Apache Software License
Classifier: Operating System :: OS Independent
Requires-Python: >=3.6
